cord64/funciones/__init__.py
cord64/funciones/convert.py
cord64-0.1.5.dist-info/METADATA
cord64-0.1.5.dist-info/WHEEL
cord64-0.1.5.dist-info/top_level.txt
cord64-0.1.5.dist-info/RECORD
