Metadata-Version: 2.1
Name: cord64
Version: 0.1.5
Summary: Convert files to Base64 and vice versa.
Home-page: https://github.com/EverGasterXd/cord64
Author: evergaster
License: MIT License
Keywords: base64 convert file
Classifier: License :: OSI Approved :: MIT License
Classifier: Operating System :: OS Independent
Classifier: Development Status :: 4 - Beta
Classifier: Natural Language :: English
Classifier: Operating System :: Microsoft :: Windows :: Windows 10
Classifier: Programming Language :: Python :: 3
Classifier: Programming Language :: Python :: 3.9
Classifier: Topic :: Internet
